README.md
pyproject.toml
setup.cfg
setup.py
src/pyrippleapi/__init__.py
src/pyrippleapi/api.py
src/pyrippleapi/exceptions.py
src/pyrippleapi/generation_asset.py
src/pyrippleapi.egg-info/PKG-INFO
src/pyrippleapi.egg-info/SOURCES.txt
src/pyrippleapi.egg-info/dependency_links.txt
src/pyrippleapi.egg-info/requires.txt
src/pyrippleapi.egg-info/top_level.txt