Metadata-Version: 2.1
Name: pyrippleapi
Version: 2024.5.3
Summary: Ripple energy api wrapper
Home-page: https://github.com/ryanbdclark/pyrippleapi
Author: Ryan Clark
Keywords: ripple,api,energy
Classifier: License :: OSI Approved :: MIT License
Classifier: Programming Language :: Python :: 3.10
Requires-Python: >=3.10
